google_auth_plugins/__init__.py
google_auth_plugins/dwd_credentials.py
google_auth_plugins-1.0.0.dist-info/LICENSE
google_auth_plugins-1.0.0.dist-info/WHEEL
google_auth_plugins-1.0.0.dist-info/METADATA
google_auth_plugins-1.0.0.dist-info/RECORD
