Metadata-Version: 2.1
Name: google-auth-plugins
Version: 1.0.0
Summary: A set of custom plugins for Google Authentication Library
Author-email: Loïc Sikidi <me@lsikidi.org>
Requires-Python: >=3.7
Classifier: License :: OSI Approved :: Apache Software License
Classifier: Programming Language :: Python :: 3 :: Only
Classifier: Programming Language :: Python :: 3
Classifier: Programming Language :: Python :: 3.7
Classifier: Programming Language :: Python :: 3.8
Classifier: Programming Language :: Python :: 3.9
Classifier: Programming Language :: Python :: 3.10
Classifier: Programming Language :: Python :: 3.11
Classifier: Development Status :: 4 - Beta
Classifier: Intended Audience :: Developers
Classifier: Operating System :: POSIX
Classifier: Operating System :: Microsoft :: Windows
Classifier: Operating System :: MacOS :: MacOS X
Classifier: Operating System :: OS Independent
Classifier: Topic :: Internet :: WWW/HTTP
Classifier: Topic :: Security
Requires-Dist: google-auth >= 2.0.0
Requires-Dist: requests
Requires-Dist: build ; extra == "dev"
Requires-Dist: bump >= 1.3.2 ; extra == "dev"
Requires-Dist: google-auth-plugins[test,lint] ; extra == "dev"
Requires-Dist: bandit ; extra == "lint"
Requires-Dist: black ; extra == "lint"
Requires-Dist: isort ; extra == "lint"
Requires-Dist: interrogate ; extra == "lint"
Requires-Dist: mypy ; extra == "lint"
Requires-Dist: pytest ; extra == "test"
Requires-Dist: pytest-cov ; extra == "test"
Requires-Dist: coverage[toml] ; extra == "test"
Provides-Extra: dev
Provides-Extra: lint
Provides-Extra: test
